specsync_bridge/__init__.py
specsync_bridge/cli.py
specsync_bridge/detector.py
specsync_bridge/extractor.py
specsync_bridge/models.py
specsync_bridge/role_detector.py
specsync_bridge/setup_wizard.py
specsync_bridge/sync.py
specsync_bridge-0.2.0.dist-info/licenses/LICENSE
specsync_bridge-0.2.0.dist-info/METADATA
specsync_bridge-0.2.0.dist-info/WHEEL
specsync_bridge-0.2.0.dist-info/entry_points.txt
specsync_bridge-0.2.0.dist-info/top_level.txt
specsync_bridge-0.2.0.dist-info/RECORD
