Metadata-Version: 2.4
Name: specsync-bridge
Version: 0.2.0
Summary: Cross-repository API contract synchronization for SpecSync
Author: SpecSync Team
License: MIT
Project-URL: Homepage, https://github.com/specsync/specsync-bridge
Keywords: api,contract,sync,validation,drift-detection
Classifier: Development Status :: 4 - Beta
Classifier: Intended Audience :: Developers
Classifier: License :: OSI Approved :: MIT License
Classifier: Programming Language :: Python :: 3
Classifier: Programming Language :: Python :: 3.9
Classifier: Programming Language :: Python :: 3.10
Classifier: Programming Language :: Python :: 3.11
Classifier: Programming Language :: Python :: 3.12
Requires-Python: >=3.9
License-File: LICENSE
Requires-Dist: pyyaml>=6.0
Dynamic: license-file
